{"id":"2749e402ab4c70b29a53c6adc5e1e2c3","movie":"solarsystem","name":"texts","transition":"alpha","time":1,"assets":{"4b251d8a59":{"order":0,"name":"title.png","type":"picture","time":5,"action":"","frames":1,"frtime":100,"file":{"@1":"text\/title.png","@2":"text\/title.png","@3":"text\/title.png","@4":"text\/title.png","@5":"text\/title.png"}},"066d9566e7":{"order":1,"name":"sizewarning.png","type":"picture","time":5,"action":"loop","frames":1,"frtime":100,"file":{"@1":"text\/sizewarning.png","@2":"text\/sizewarning.png","@3":"text\/sizewarning.png","@4":"text\/sizewarning.png","@5":"text\/sizewarning.png"}}}}